repetition_pos_ex_forex_next3
