Metadata-Version: 1.0
Name: repetition-pos-ex-forex-next3
Version: 1.22
Summary: repetition_pos_ex_forex_next3
Home-page: UNKNOWN
Author: omid
Author-email: UNKNOWN
License: UNKNOWN
Platform: UNKNOWN
